quickpython/__init__.py
quickpython/cli.py
quickpython/examples/__init__.py
quickpython/examples/connect.py
quickpython/examples/eightpuzzle.py
quickpython/examples/hangman.py
quickpython/examples/memory.py
quickpython/examples/minesweeper.py
quickpython/examples/simon.py
quickpython/examples/tictactoe.py
quickpython/examples/towers.py
quickpython/examples/uno.py
quickpython/examples/zigzag.py
quickpython/extensions.py
quickpython-0.1.4.dist-info/entry_points.txt
quickpython-0.1.4.dist-info/LICENSE
quickpython-0.1.4.dist-info/WHEEL
quickpython-0.1.4.dist-info/METADATA
quickpython-0.1.4.dist-info/RECORD
