Metadata-Version: 2.1
Name: quickpython
Version: 0.1.4
Summary: A retro interactive coding environment powered by Python and nostalgia 
License: MIT
Author: Timothy Crosley
Author-email: timothy.crosley@gmail.com
Requires-Python: >=3.6.1,<4.0.0
Classifier: License :: OSI Approved :: MIT License
Classifier: Programming Language :: Python :: 3
Classifier: Programming Language :: Python :: 3.7
Classifier: Programming Language :: Python :: 3.8
Classifier: Programming Language :: Python :: 3.9
Requires-Dist: black (>=20.8b1,<21.0)
Requires-Dist: colorama (>=0.4.4,<0.5.0)
Requires-Dist: ipdb (>=0.13.4,<0.14.0)
Requires-Dist: isort (>=5.4.2,<6.0.0)
Requires-Dist: prompt-toolkit (>=3.0.6,<4.0.0)
Requires-Dist: pyfiglet (>=0.8.post1,<0.9)
